pcnn/__init__.py
pcnn/ccnn.py
pcnn/metrics.py
pcnn/pcnn.py
pcnn/threshold.py
pcnn/tools.py
pcnn-0.1.dist-info/LICENSE
pcnn-0.1.dist-info/METADATA
pcnn-0.1.dist-info/WHEEL
pcnn-0.1.dist-info/top_level.txt
pcnn-0.1.dist-info/RECORD
