Metadata-Version: 2.1
Name: pcnn
Version: 0.1
Summary: A toolbox of Pulse Coupled Neural Network (PCNN) for image processing
Home-page: https://github.com/lidezhenw/pcnn
Author: lidezhen
Author-email: lidezhen <lidezhenw@163.com>
License: GNU GENERAL PUBLIC LICENSE
Project-URL: Homepage, https://github.com/lidezhenw/pcnn
Project-URL: Issues, https://github.com/lidezhenw/pcnn/issues
Keywords: Image Processing
Classifier: Programming Language :: Python :: 3
Classifier: License :: OSI Approved :: GNU General Public License v3 (GPLv3)
Classifier: Operating System :: OS Independent
Requires-Python: >=3
License-File: LICENSE
Requires-Dist: numpy
Requires-Dist: scipy
Requires-Dist: opencv-python
